odoo/addons/delivery_carrier_pricelist/README.rst
odoo/addons/delivery_carrier_pricelist/__init__.py
odoo/addons/delivery_carrier_pricelist/__manifest__.py
odoo/addons/delivery_carrier_pricelist/i18n/delivery_carrier_pricelist.pot
odoo/addons/delivery_carrier_pricelist/i18n/es.po
odoo/addons/delivery_carrier_pricelist/i18n/es_CL.po
odoo/addons/delivery_carrier_pricelist/i18n/es_VE.po
odoo/addons/delivery_carrier_pricelist/models/__init__.py
odoo/addons/delivery_carrier_pricelist/models/delivery_carrier.py
odoo/addons/delivery_carrier_pricelist/models/stock_picking.py
odoo/addons/delivery_carrier_pricelist/readme/CONTRIBUTORS.rst
odoo/addons/delivery_carrier_pricelist/readme/DESCRIPTION.rst
odoo/addons/delivery_carrier_pricelist/static/description/icon.png
odoo/addons/delivery_carrier_pricelist/static/description/index.html
odoo/addons/delivery_carrier_pricelist/tests/__init__.py
odoo/addons/delivery_carrier_pricelist/tests/test_delivery_pricelist.py
odoo/addons/delivery_carrier_pricelist/wizards/__init__.py
odoo/addons/delivery_carrier_pricelist/wizards/choose_delivery_carrier.py
odoo13_addon_delivery_carrier_pricelist-13.0.1.0.1.dev12.dist-info/METADATA
odoo13_addon_delivery_carrier_pricelist-13.0.1.0.1.dev12.dist-info/WHEEL
odoo13_addon_delivery_carrier_pricelist-13.0.1.0.1.dev12.dist-info/top_level.txt
odoo13_addon_delivery_carrier_pricelist-13.0.1.0.1.dev12.dist-info/RECORD
